{
  "version": "8",
  "dialect": "postgres",
  "id": "a0102f54-b93c-4ab0-9eca-0905d47fc9e5",
  "prevIds": [
    "00000000-0000-0000-0000-000000000000"
  ],
  "ddl": [
    {
      "isRlsEnabled": false,
      "name": "leads",
      "entityType": "tables",
      "schema": "public"
    },
    {
      "type": "serial",
      "typeSchema": null,
      "notNull": true,
      "dimensions": 0,
      "default": null,
      "generated": null,
      "identity": null,
      "name": "id",
      "entityType": "columns",
      "schema": "public",
      "table": "leads"
    },
    {
      "type": "text",
      "typeSchema": null,
      "notNull": true,
      "dimensions": 0,
      "default": null,
      "generated": null,
      "identity": null,
      "name": "nom",
      "entityType": "columns",
      "schema": "public",
      "table": "leads"
    },
    {
      "type": "text",
      "typeSchema": null,
      "notNull": true,
      "dimensions": 0,
      "default": null,
      "generated": null,
      "identity": null,
      "name": "email",
      "entityType": "columns",
      "schema": "public",
      "table": "leads"
    },
    {
      "type": "text",
      "typeSchema": null,
      "notNull": false,
      "dimensions": 0,
      "default": null,
      "generated": null,
      "identity": null,
      "name": "organisation",
      "entityType": "columns",
      "schema": "public",
      "table": "leads"
    },
    {
      "type": "text",
      "typeSchema": null,
      "notNull": true,
      "dimensions": 0,
      "default": null,
      "generated": null,
      "identity": null,
      "name": "message",
      "entityType": "columns",
      "schema": "public",
      "table": "leads"
    },
    {
      "type": "text",
      "typeSchema": null,
      "notNull": true,
      "dimensions": 0,
      "default": "'fr'",
      "generated": null,
      "identity": null,
      "name": "langue",
      "entityType": "columns",
      "schema": "public",
      "table": "leads"
    },
    {
      "type": "timestamp",
      "typeSchema": null,
      "notNull": false,
      "dimensions": 0,
      "default": "now()",
      "generated": null,
      "identity": null,
      "name": "created_at",
      "entityType": "columns",
      "schema": "public",
      "table": "leads"
    },
    {
      "columns": [
        "id"
      ],
      "nameExplicit": false,
      "name": "leads_pkey",
      "schema": "public",
      "table": "leads",
      "entityType": "pks"
    }
  ],
  "renames": []
}